helloworld.py
jamesmoon_world-0.0.1.dist-info/LICENSE
jamesmoon_world-0.0.1.dist-info/METADATA
jamesmoon_world-0.0.1.dist-info/WHEEL
jamesmoon_world-0.0.1.dist-info/top_level.txt
jamesmoon_world-0.0.1.dist-info/RECORD
