Metadata-Version: 2.1
Name: jamesmoon-world
Version: 0.0.1
Summary: Say hello!
Home-page: https://github.com/moonchangin/helloworld_pypi
Author: Chang In Moon
Author-email: changin.moon@bcm.edu
License: UNKNOWN
Platform: UNKNOWN
Classifier: Programming Language :: Python :: 3
Classifier: Programming Language :: Python :: 3.6
Classifier: Programming Language :: Python :: 3.7
Classifier: License :: OSI Approved :: GNU General Public License v3 (GPLv3)
Classifier: Operating System :: OS Independent
License-File: LICENSE
Provides-Extra: dev
Requires-Dist: pytest (>=3.7) ; extra == 'dev'
